LICENSE
MANIFEST.in
README.md
setup.py
testflows.recipes.egg-info/PKG-INFO
testflows.recipes.egg-info/SOURCES.txt
testflows.recipes.egg-info/dependency_links.txt
testflows.recipes.egg-info/not-zip-safe
testflows.recipes.egg-info/requires.txt
testflows.recipes.egg-info/top_level.txt
testflows/recipes/__init__.py
testflows/recipes/core.py