Metadata-Version: 2.1
Name: testflows.recipes
Version: 1.7.211130.1020032
Summary: TestFlows - Recipes
Home-page: https://github.com/testflows/testflows-recipes
Author: Vitaliy Zakaznikov
Author-email: vzakaznikov@testflows.com
License: Apache-2.0
Platform: UNKNOWN
Classifier: Development Status :: 2 - Pre-Alpha
Classifier: Programming Language :: Python :: 3
Classifier: License :: OSI Approved :: Apache Software License
Classifier: Operating System :: POSIX :: Linux
Requires-Python: >=3.6
